Sanic193ZhongwenWendang/README.md
Sanic193ZhongwenWendang/__init__.py
Sanic193ZhongwenWendang/__main__.py
Sanic193ZhongwenWendang/file.epub
Sanic193ZhongwenWendang/index.html
Sanic193ZhongwenWendang/css/__init__.py
Sanic193ZhongwenWendang/css/annotations.css
Sanic193ZhongwenWendang/css/main.css
Sanic193ZhongwenWendang/css/normalize.css
Sanic193ZhongwenWendang/css/popup.css
Sanic193ZhongwenWendang/font/__init__.py
Sanic193ZhongwenWendang/font/fontello.eot
Sanic193ZhongwenWendang/font/fontello.svg
Sanic193ZhongwenWendang/font/fontello.ttf
Sanic193ZhongwenWendang/font/fontello.woff
Sanic193ZhongwenWendang/img/__init__.py
Sanic193ZhongwenWendang/img/annotator-glyph-sprite.png
Sanic193ZhongwenWendang/img/annotator-icon-sprite.png
Sanic193ZhongwenWendang/img/apple-touch-icon.png
Sanic193ZhongwenWendang/img/cancelfullscreen.png
Sanic193ZhongwenWendang/img/close.png
Sanic193ZhongwenWendang/img/fullscreen.png
Sanic193ZhongwenWendang/img/loader.gif
Sanic193ZhongwenWendang/img/menu-icon.png
Sanic193ZhongwenWendang/img/save.png
Sanic193ZhongwenWendang/img/saved.png
Sanic193ZhongwenWendang/img/settings-s.png
Sanic193ZhongwenWendang/img/settings.png
Sanic193ZhongwenWendang/img/star.png
Sanic193ZhongwenWendang/js/__init__.py
Sanic193ZhongwenWendang/js/epub.js
Sanic193ZhongwenWendang/js/epub.min.js
Sanic193ZhongwenWendang/js/epub.min.map
Sanic193ZhongwenWendang/js/hooks.min.js
Sanic193ZhongwenWendang/js/hooks.min.map
Sanic193ZhongwenWendang/js/reader.js
Sanic193ZhongwenWendang/js/reader.js.map
Sanic193ZhongwenWendang/js/reader.min.js
Sanic193ZhongwenWendang/js/reader.min.map
Sanic193ZhongwenWendang/js/hooks/__init__.py
Sanic193ZhongwenWendang/js/hooks/extensions/__init__.py
Sanic193ZhongwenWendang/js/hooks/extensions/highlight.js
Sanic193ZhongwenWendang/js/libs/__init__.py
Sanic193ZhongwenWendang/js/libs/jquery.min.js
Sanic193ZhongwenWendang/js/libs/localforage.min.js
Sanic193ZhongwenWendang/js/libs/screenfull.js
Sanic193ZhongwenWendang/js/libs/screenfull.min.js
sanic_19_3_zhongwen_wendang-2024.3.4.0.dist-info/METADATA
sanic_19_3_zhongwen_wendang-2024.3.4.0.dist-info/WHEEL
sanic_19_3_zhongwen_wendang-2024.3.4.0.dist-info/entry_points.txt
sanic_19_3_zhongwen_wendang-2024.3.4.0.dist-info/top_level.txt
sanic_19_3_zhongwen_wendang-2024.3.4.0.dist-info/RECORD
